{
    "objects": [
        {
            "geometryType": "obb",
            "obb": {
                "xc": 276.5,
                "yc": 107.50000762939453,
                "w": 142.7420196533203,
                "h": 57.85079574584961,
                "theta": 172.60598754882812
            },
            "height": 985,
            "width": 736
        },
        {
            "geometryType": "obb",
            "obb": {
                "xc": 411.0,
                "yc": 101.0,
                "w": 81.22067260742188,
                "h": 60.39207458496094,
                "theta": 7.028395652770996
            },
            "height": 985,
            "width": 736
        },
        {
            "geometryType": "obb",
            "obb": {
                "xc": 340.3026123046875,
                "yc": 163.48512268066406,
                "w": 268.4624328613281,
                "h": 71.01253509521484,
                "theta": 177.1844482421875
            },
            "height": 985,
            "width": 736
        },
        {
            "geometryType": "obb",
            "obb": {
                "xc": 257.4184875488281,
                "yc": 232.0126953125,
                "w": 210.5928955078125,
                "h": 71.73391723632812,
                "theta": 161.36187744140625
            },
            "height": 985,
            "width": 736
        },
        {
            "geometryType": "obb",
            "obb": {
                "xc": 448.85223388671875,
                "yc": 227.9915771484375,
                "w": 170.04641723632812,
                "h": 63.58594512939453,
                "theta": 14.574216842651367
            },
            "height": 985,
            "width": 736
        }
    ]
}