{
    "objects": [
        {
            "geometryType": "obb",
            "obb": {
                "xc": 308.015869140625,
                "yc": 274.4403381347656,
                "w": 99.28581237792969,
                "h": 20.041324615478516,
                "theta": 157.04591369628906
            },
            "height": 500,
            "width": 800
        },
        {
            "geometryType": "obb",
            "obb": {
                "xc": 415.5925598144531,
                "yc": 250.477294921875,
                "w": 97.0472412109375,
                "h": 23.683298110961914,
                "theta": 179.18154907226562
            },
            "height": 500,
            "width": 800
        },
        {
            "geometryType": "obb",
            "obb": {
                "xc": 525.8255615234375,
                "yc": 271.2279357910156,
                "w": 111.61494445800781,
                "h": 22.479480743408203,
                "theta": 21.605525970458984
            },
            "height": 500,
            "width": 800
        },
        {
            "geometryType": "obb",
            "obb": {
                "xc": 340.1414794921875,
                "yc": 280.7452697753906,
                "w": 64.97154235839844,
                "h": 19.367835998535156,
                "theta": 164.05460357666016
            },
            "height": 500,
            "width": 800
        },
        {
            "geometryType": "obb",
            "obb": {
                "xc": 414.17431640625,
                "yc": 270.7729797363281,
                "w": 75.99845886230469,
                "h": 18.60393524169922,
                "theta": 178.4088592529297
            },
            "height": 500,
            "width": 800
        },
        {
            "geometryType": "obb",
            "obb": {
                "xc": 495.9861145019531,
                "yc": 279.99578857421875,
                "w": 71.25481414794922,
                "h": 15.892404556274414,
                "theta": 16.8583984375
            },
            "height": 500,
            "width": 800
        }
    ]
}