{
    "objects": [
        {
            "geometryType": "obb",
            "obb": {
                "xc": 346.0,
                "yc": 463.5,
                "w": 24.0,
                "h": 15.0,
                "theta": 180.0
            },
            "height": 637,
            "width": 733
        },
        {
            "geometryType": "obb",
            "obb": {
                "xc": 305.2446594238281,
                "yc": 311.8526306152344,
                "w": 131.28140258789062,
                "h": 43.35414505004883,
                "theta": 158.101806640625
            },
            "height": 637,
            "width": 733
        },
        {
            "geometryType": "obb",
            "obb": {
                "xc": 410.24237060546875,
                "yc": 321.2708435058594,
                "w": 87.6522216796875,
                "h": 35.85456466674805,
                "theta": 31.476839065551758
            },
            "height": 637,
            "width": 733
        },
        {
            "geometryType": "obb",
            "obb": {
                "xc": 315.3144226074219,
                "yc": 482.0824890136719,
                "w": 81.0574722290039,
                "h": 29.07730484008789,
                "theta": 21.037511825561523
            },
            "height": 637,
            "width": 733
        },
        {
            "geometryType": "obb",
            "obb": {
                "xc": 385.3140563964844,
                "yc": 479.0292663574219,
                "w": 62.13296890258789,
                "h": 26.64902114868164,
                "theta": 154.35899353027344
            },
            "height": 637,
            "width": 733
        }
    ]
}