{
    "objects": [
        {
            "geometryType": "obb",
            "obb": {
                "xc": 487.1574401855469,
                "yc": 344.43212890625,
                "w": 225.74473571777344,
                "h": 75.43601989746094,
                "theta": 169.5483627319336
            },
            "height": 720,
            "width": 1280
        },
        {
            "geometryType": "obb",
            "obb": {
                "xc": 337.117919921875,
                "yc": 578.8251342773438,
                "w": 179.32806396484375,
                "h": 51.24363708496094,
                "theta": 54.544525146484375
            },
            "height": 720,
            "width": 1280
        },
        {
            "geometryType": "obb",
            "obb": {
                "xc": 304.1760559082031,
                "yc": 429.826416015625,
                "w": 89.69652557373047,
                "h": 30.558134078979492,
                "theta": 98.53076553344727
            },
            "height": 720,
            "width": 1280
        },
        {
            "geometryType": "obb",
            "obb": {
                "xc": 367.2831726074219,
                "yc": 295.14874267578125,
                "w": 172.4680633544922,
                "h": 40.84541320800781,
                "theta": 127.4926528930664
            },
            "height": 720,
            "width": 1280
        },
        {
            "geometryType": "obb",
            "obb": {
                "xc": 478.056884765625,
                "yc": 193.62173461914062,
                "w": 111.89280700683594,
                "h": 33.389102935791016,
                "theta": 151.14434051513672
            },
            "height": 720,
            "width": 1280
        },
        {
            "geometryType": "obb",
            "obb": {
                "xc": 594.6295166015625,
                "yc": 153.16262817382812,
                "w": 118.82760620117188,
                "h": 44.63609313964844,
                "theta": 173.23382568359375
            },
            "height": 720,
            "width": 1280
        },
        {
            "geometryType": "obb",
            "obb": {
                "xc": 763.4405517578125,
                "yc": 167.9365692138672,
                "w": 192.19766235351562,
                "h": 41.53473663330078,
                "theta": 27.16498374938965
            },
            "height": 720,
            "width": 1280
        },
        {
            "geometryType": "obb",
            "obb": {
                "xc": 881.998779296875,
                "yc": 304.95794677734375,
                "w": 162.39419555664062,
                "h": 48.24014663696289,
                "theta": 78.8453369140625
            },
            "height": 720,
            "width": 1280
        },
        {
            "geometryType": "obb",
            "obb": {
                "xc": 790.2501220703125,
                "yc": 567.2500610351562,
                "w": 101.82337951660156,
                "h": 37.47665786743164,
                "theta": 135.0
            },
            "height": 720,
            "width": 1280
        },
        {
            "geometryType": "obb",
            "obb": {
                "xc": 865.003662109375,
                "yc": 455.88104248046875,
                "w": 158.52684020996094,
                "h": 39.17060089111328,
                "theta": 114.96278762817383
            },
            "height": 720,
            "width": 1280
        },
        {
            "geometryType": "obb",
            "obb": {
                "xc": 347.5496826171875,
                "yc": 486.8702392578125,
                "w": 176.08018493652344,
                "h": 44.88876724243164,
                "theta": 80.89540100097656
            },
            "height": 720,
            "width": 1280
        },
        {
            "geometryType": "obb",
            "obb": {
                "xc": 388.82171630859375,
                "yc": 325.0920715332031,
                "w": 149.55181884765625,
                "h": 38.94552230834961,
                "theta": 126.13537979125977
            },
            "height": 720,
            "width": 1280
        },
        {
            "geometryType": "obb",
            "obb": {
                "xc": 511.00006103515625,
                "yc": 215.00001525878906,
                "w": 138.63621520996094,
                "h": 35.7770881652832,
                "theta": 153.43495178222656
            },
            "height": 720,
            "width": 1280
        },
        {
            "geometryType": "obb",
            "obb": {
                "xc": 682.3236694335938,
                "yc": 182.8959503173828,
                "w": 157.3791961669922,
                "h": 46.681556701660156,
                "theta": 8.746162414550781
            },
            "height": 720,
            "width": 1280
        },
        {
            "geometryType": "obb",
            "obb": {
                "xc": 810.9306030273438,
                "yc": 256.02813720703125,
                "w": 165.97491455078125,
                "h": 52.1669921875,
                "theta": 57.58769607543945
            },
            "height": 720,
            "width": 1280
        },
        {
            "geometryType": "obb",
            "obb": {
                "xc": 830.9940795898438,
                "yc": 415.6999816894531,
                "w": 165.4440155029297,
                "h": 39.133094787597656,
                "theta": 104.23727989196777
            },
            "height": 720,
            "width": 1280
        },
        {
            "geometryType": "obb",
            "obb": {
                "xc": 724.7275390625,
                "yc": 564.37451171875,
                "w": 163.7863311767578,
                "h": 36.61932373046875,
                "theta": 145.25682067871094
            },
            "height": 720,
            "width": 1280
        },
        {
            "geometryType": "obb",
            "obb": {
                "xc": 587.0,
                "yc": 216.00001525878906,
                "w": 111.00162506103516,
                "h": 28.260251998901367,
                "theta": 169.50852966308594
            },
            "height": 720,
            "width": 1280
        },
        {
            "geometryType": "obb",
            "obb": {
                "xc": 688.8218383789062,
                "yc": 213.7283935546875,
                "w": 96.16651153564453,
                "h": 28.70021629333496,
                "theta": 16.927513122558594
            },
            "height": 720,
            "width": 1280
        },
        {
            "geometryType": "obb",
            "obb": {
                "xc": 785.2755737304688,
                "yc": 319.776611328125,
                "w": 201.15625,
                "h": 54.010520935058594,
                "theta": 72.75853729248047
            },
            "height": 720,
            "width": 1280
        },
        {
            "geometryType": "obb",
            "obb": {
                "xc": 744.46875,
                "yc": 493.87744140625,
                "w": 165.79464721679688,
                "h": 40.9163818359375,
                "theta": 128.10757446289062
            },
            "height": 720,
            "width": 1280
        },
        {
            "geometryType": "obb",
            "obb": {
                "xc": 608.909912109375,
                "yc": 581.2544555664062,
                "w": 161.55491638183594,
                "h": 41.668357849121094,
                "theta": 164.8989028930664
            },
            "height": 720,
            "width": 1280
        },
        {
            "geometryType": "obb",
            "obb": {
                "xc": 440.1588134765625,
                "yc": 555.4647216796875,
                "w": 191.28106689453125,
                "h": 50.926475524902344,
                "theta": 32.47119140625
            },
            "height": 720,
            "width": 1280
        },
        {
            "geometryType": "obb",
            "obb": {
                "xc": 598.2305297851562,
                "yc": 431.5135498046875,
                "w": 374.9400634765625,
                "h": 122.65520477294922,
                "theta": 171.7759246826172
            },
            "height": 720,
            "width": 1280
        },
        {
            "geometryType": "obb",
            "obb": {
                "xc": 448.23309326171875,
                "yc": 622.5474853515625,
                "w": 82.60421752929688,
                "h": 25.89790153503418,
                "theta": 19.65382194519043
            },
            "height": 720,
            "width": 1280
        }
    ]
}