{
    "objects": [
        {
            "geometryType": "obb",
            "obb": {
                "xc": 274.0,
                "yc": 187.0,
                "w": 134.0,
                "h": 16.0,
                "theta": 180.0
            },
            "height": 537,
            "width": 800
        },
        {
            "geometryType": "obb",
            "obb": {
                "xc": 87.5,
                "yc": 155.5,
                "w": 85.0,
                "h": 25.0,
                "theta": 180.0
            },
            "height": 537,
            "width": 800
        },
        {
            "geometryType": "obb",
            "obb": {
                "xc": 102.73941040039062,
                "yc": 188.55331420898438,
                "w": 63.15116500854492,
                "h": 27.506826400756836,
                "theta": 157.5572509765625
            },
            "height": 537,
            "width": 800
        },
        {
            "geometryType": "obb",
            "obb": {
                "xc": 136.50001525878906,
                "yc": 218.50001525878906,
                "w": 39.06100082397461,
                "h": 23.92149543762207,
                "theta": 175.36454010009766
            },
            "height": 537,
            "width": 800
        },
        {
            "geometryType": "obb",
            "obb": {
                "xc": 305.531982421875,
                "yc": 159.08041381835938,
                "w": 207.86947631835938,
                "h": 43.957191467285156,
                "theta": 178.83875274658203
            },
            "height": 537,
            "width": 800
        },
        {
            "geometryType": "obb",
            "obb": {
                "xc": 453.0,
                "yc": 177.50001525878906,
                "w": 203.1472625732422,
                "h": 103.17068481445312,
                "theta": 2.834111213684082
            },
            "height": 537,
            "width": 800
        },
        {
            "geometryType": "obb",
            "obb": {
                "xc": 647.489990234375,
                "yc": 213.23675537109375,
                "w": 262.8456115722656,
                "h": 22.602497100830078,
                "theta": 0.46392330527305603
            },
            "height": 537,
            "width": 800
        },
        {
            "geometryType": "obb",
            "obb": {
                "xc": 663.5,
                "yc": 156.49998474121094,
                "w": 49.930747985839844,
                "h": 15.649934768676758,
                "theta": 152.40270614624023
            },
            "height": 537,
            "width": 800
        },
        {
            "geometryType": "obb",
            "obb": {
                "xc": 713.9988403320312,
                "yc": 176.2805938720703,
                "w": 139.03236389160156,
                "h": 46.449615478515625,
                "theta": 178.7635955810547
            },
            "height": 537,
            "width": 800
        },
        {
            "geometryType": "obb",
            "obb": {
                "xc": 169.02493286132812,
                "yc": 154.22328186035156,
                "w": 58.68926239013672,
                "h": 20.43613052368164,
                "theta": 178.0250701904297
            },
            "height": 537,
            "width": 800
        },
        {
            "geometryType": "obb",
            "obb": {
                "xc": 24.5,
                "yc": 156.0,
                "w": 31.0,
                "h": 12.0,
                "theta": -0.0
            },
            "height": 537,
            "width": 800
        },
        {
            "geometryType": "obb",
            "obb": {
                "xc": 10.357976913452148,
                "yc": 183.22763061523438,
                "w": 17.029272079467773,
                "h": 7.4853949546813965,
                "theta": 176.42366790771484
            },
            "height": 537,
            "width": 800
        },
        {
            "geometryType": "obb",
            "obb": {
                "xc": 21.0,
                "yc": 194.5,
                "w": 38.0,
                "h": 9.0,
                "theta": 180.0
            },
            "height": 537,
            "width": 800
        },
        {
            "geometryType": "obb",
            "obb": {
                "xc": 143.95579528808594,
                "yc": 178.8397979736328,
                "w": 19.02629852294922,
                "h": 12.929472923278809,
                "theta": 93.01278734207153
            },
            "height": 537,
            "width": 800
        },
        {
            "geometryType": "obb",
            "obb": {
                "xc": 72.5,
                "yc": 219.5,
                "w": 59.0,
                "h": 15.0,
                "theta": -0.0
            },
            "height": 537,
            "width": 800
        },
        {
            "geometryType": "obb",
            "obb": {
                "xc": 213.5,
                "yc": 215.5,
                "w": 19.0,
                "h": 15.0,
                "theta": 180.0
            },
            "height": 537,
            "width": 800
        },
        {
            "geometryType": "obb",
            "obb": {
                "xc": 289.1297607421875,
                "yc": 210.82162475585938,
                "w": 83.595947265625,
                "h": 27.657363891601562,
                "theta": 171.02737426757812
            },
            "height": 537,
            "width": 800
        },
        {
            "geometryType": "obb",
            "obb": {
                "xc": 172.51376342773438,
                "yc": 186.45413208007812,
                "w": 27.872745513916016,
                "h": 19.922788619995117,
                "theta": 16.699243545532227
            },
            "height": 537,
            "width": 800
        },
        {
            "geometryType": "obb",
            "obb": {
                "xc": 436.0,
                "yc": 214.0,
                "w": 36.0,
                "h": 16.0,
                "theta": 0.0
            },
            "height": 537,
            "width": 800
        },
        {
            "geometryType": "obb",
            "obb": {
                "xc": 715.9862670898438,
                "yc": 144.26243591308594,
                "w": 64.12178802490234,
                "h": 12.509002685546875,
                "theta": 3.012787342071533
            },
            "height": 537,
            "width": 800
        },
        {
            "geometryType": "obb",
            "obb": {
                "xc": 768.3400268554688,
                "yc": 160.37997436523438,
                "w": 19.799999237060547,
                "h": 8.600000381469727,
                "theta": 36.86989974975586
            },
            "height": 537,
            "width": 800
        },
        {
            "geometryType": "obb",
            "obb": {
                "xc": 154.90988159179688,
                "yc": 289.5872802734375,
                "w": 65.99141693115234,
                "h": 13.853036880493164,
                "theta": 0.9240454435348511
            },
            "height": 537,
            "width": 800
        },
        {
            "geometryType": "obb",
            "obb": {
                "xc": 142.97286987304688,
                "yc": 283.92987060546875,
                "w": 90.99213409423828,
                "h": 25.542484283447266,
                "theta": 177.27368927001953
            },
            "height": 537,
            "width": 800
        },
        {
            "geometryType": "obb",
            "obb": {
                "xc": 199.617919921875,
                "yc": 286.6157531738281,
                "w": 20.815784454345703,
                "h": 19.692392349243164,
                "theta": 7.594643592834473
            },
            "height": 537,
            "width": 800
        },
        {
            "geometryType": "obb",
            "obb": {
                "xc": 236.5,
                "yc": 266.5,
                "w": 13.0,
                "h": 9.0,
                "theta": -0.0
            },
            "height": 537,
            "width": 800
        },
        {
            "geometryType": "obb",
            "obb": {
                "xc": 561.0492553710938,
                "yc": 145.4590301513672,
                "w": 15.02893352508545,
                "h": 12.493931770324707,
                "theta": 5.19442892074585
            },
            "height": 537,
            "width": 800
        },
        {
            "geometryType": "obb",
            "obb": {
                "xc": 385.0,
                "yc": 484.5,
                "w": 128.0,
                "h": 27.0,
                "theta": 180.0
            },
            "height": 537,
            "width": 800
        },
        {
            "geometryType": "obb",
            "obb": {
                "xc": 468.0,
                "yc": 487.0,
                "w": 30.0,
                "h": 20.0,
                "theta": 180.0
            },
            "height": 537,
            "width": 800
        }
    ]
}