{
    "objects": [
        {
            "geometryType": "obb",
            "obb": {
                "xc": 538.02490234375,
                "yc": 470.0933837890625,
                "w": 120.71495056152344,
                "h": 36.523677825927734,
                "theta": 165.0685806274414
            },
            "height": 947,
            "width": 1280
        },
        {
            "geometryType": "obb",
            "obb": {
                "xc": 715.5720825195312,
                "yc": 470.6938171386719,
                "w": 147.10540771484375,
                "h": 39.685829162597656,
                "theta": 7.0283966064453125
            },
            "height": 947,
            "width": 1280
        },
        {
            "geometryType": "obb",
            "obb": {
                "xc": 623.0,
                "yc": 461.5,
                "w": 32.0,
                "h": 29.0,
                "theta": -0.0
            },
            "height": 947,
            "width": 1280
        },
        {
            "geometryType": "obb",
            "obb": {
                "xc": 993.5,
                "yc": 823.5000610351562,
                "w": 34.70180892944336,
                "h": 10.088824272155762,
                "theta": 1.7899105548858643
            },
            "height": 947,
            "width": 1280
        },
        {
            "geometryType": "obb",
            "obb": {
                "xc": 1233.0,
                "yc": 829.0,
                "w": 20.0,
                "h": 8.0,
                "theta": -0.0
            },
            "height": 947,
            "width": 1280
        },
        {
            "geometryType": "obb",
            "obb": {
                "xc": 523.718017578125,
                "yc": 873.0487060546875,
                "w": 50.03998947143555,
                "h": 14.988016128540039,
                "theta": 2.2906100749969482
            },
            "height": 947,
            "width": 1280
        },
        {
            "geometryType": "obb",
            "obb": {
                "xc": 524.0,
                "yc": 785.0,
                "w": 54.0,
                "h": 10.0,
                "theta": -0.0
            },
            "height": 947,
            "width": 1280
        },
        {
            "geometryType": "obb",
            "obb": {
                "xc": 1243.3756103515625,
                "yc": 931.1834716796875,
                "w": 30.133325576782227,
                "h": 23.657302856445312,
                "theta": 7.594643592834473
            },
            "height": 947,
            "width": 1280
        },
        {
            "geometryType": "obb",
            "obb": {
                "xc": 468.067626953125,
                "yc": 865.613037109375,
                "w": 78.05353546142578,
                "h": 50.76890563964844,
                "theta": 2.7927021980285645
            },
            "height": 947,
            "width": 1280
        },
        {
            "geometryType": "obb",
            "obb": {
                "xc": 999.4813232421875,
                "yc": 924.6260375976562,
                "w": 23.27092933654785,
                "h": 15.980037689208984,
                "theta": 87.1375961303711
            },
            "height": 947,
            "width": 1280
        }
    ]
}