{
    "objects": [
        {
            "geometryType": "obb",
            "obb": {
                "xc": 369.84503173828125,
                "yc": 99.25205993652344,
                "w": 126.80223846435547,
                "h": 35.845882415771484,
                "theta": 176.05481719970703
            },
            "height": 768,
            "width": 859
        },
        {
            "geometryType": "obb",
            "obb": {
                "xc": 568.7981567382812,
                "yc": 103.73707580566406,
                "w": 102.92008972167969,
                "h": 38.97013854980469,
                "theta": 13.284866333007812
            },
            "height": 768,
            "width": 859
        },
        {
            "geometryType": "obb",
            "obb": {
                "xc": 161.4129638671875,
                "yc": 461.84588623046875,
                "w": 157.163330078125,
                "h": 52.11814880371094,
                "theta": 16.323047637939453
            },
            "height": 768,
            "width": 859
        },
        {
            "geometryType": "obb",
            "obb": {
                "xc": 289.8384704589844,
                "yc": 539.5923461914062,
                "w": 56.6579475402832,
                "h": 45.25619125366211,
                "theta": 15.255118370056152
            },
            "height": 768,
            "width": 859
        },
        {
            "geometryType": "obb",
            "obb": {
                "xc": 372.2689208984375,
                "yc": 562.9635009765625,
                "w": 75.79782104492188,
                "h": 40.29033279418945,
                "theta": 8.972625732421875
            },
            "height": 768,
            "width": 859
        },
        {
            "geometryType": "obb",
            "obb": {
                "xc": 508.291748046875,
                "yc": 569.5947875976562,
                "w": 145.1815948486328,
                "h": 44.119407653808594,
                "theta": 175.51539611816406
            },
            "height": 768,
            "width": 859
        },
        {
            "geometryType": "obb",
            "obb": {
                "xc": 643.43603515625,
                "yc": 541.2022094726562,
                "w": 92.21714782714844,
                "h": 40.79366683959961,
                "theta": 156.97450256347656
            },
            "height": 768,
            "width": 859
        },
        {
            "geometryType": "obb",
            "obb": {
                "xc": 737.5543212890625,
                "yc": 457.7153625488281,
                "w": 56.95222473144531,
                "h": 31.764965057373047,
                "theta": 147.42594146728516
            },
            "height": 768,
            "width": 859
        },
        {
            "geometryType": "obb",
            "obb": {
                "xc": 489.5325012207031,
                "yc": 420.0904541015625,
                "w": 97.86617279052734,
                "h": 90.79924774169922,
                "theta": 92.04540848731995
            },
            "height": 768,
            "width": 859
        }
    ]
}