{
    "objects": [
        {
            "geometryType": "obb",
            "obb": {
                "xc": 443.17852783203125,
                "yc": 379.19036865234375,
                "w": 191.23495483398438,
                "h": 38.87731170654297,
                "theta": 151.17444610595703
            },
            "height": 810,
            "width": 1080
        },
        {
            "geometryType": "obb",
            "obb": {
                "xc": 594.238037109375,
                "yc": 373.73626708984375,
                "w": 137.2245635986328,
                "h": 39.448753356933594,
                "theta": 34.950653076171875
            },
            "height": 810,
            "width": 1080
        },
        {
            "geometryType": "obb",
            "obb": {
                "xc": 582.0447387695312,
                "yc": 539.2657470703125,
                "w": 225.84707641601562,
                "h": 51.68192672729492,
                "theta": 140.2738914489746
            },
            "height": 810,
            "width": 1080
        },
        {
            "geometryType": "obb",
            "obb": {
                "xc": 361.5357360839844,
                "yc": 543.30078125,
                "w": 126.52661895751953,
                "h": 41.851261138916016,
                "theta": 57.067771911621094
            },
            "height": 810,
            "width": 1080
        },
        {
            "geometryType": "obb",
            "obb": {
                "xc": 115.18464660644531,
                "yc": 510.00848388671875,
                "w": 86.81034851074219,
                "h": 36.60276794433594,
                "theta": 79.62415313720703
            },
            "height": 810,
            "width": 1080
        },
        {
            "geometryType": "obb",
            "obb": {
                "xc": 139.9339599609375,
                "yc": 588.4811401367188,
                "w": 81.97651672363281,
                "h": 52.25518035888672,
                "theta": 60.945396423339844
            },
            "height": 810,
            "width": 1080
        },
        {
            "geometryType": "obb",
            "obb": {
                "xc": 188.03768920898438,
                "yc": 683.48291015625,
                "w": 99.56098937988281,
                "h": 66.70503234863281,
                "theta": 65.55604553222656
            },
            "height": 810,
            "width": 1080
        },
        {
            "geometryType": "obb",
            "obb": {
                "xc": 651.5000610351562,
                "yc": 436.0000305175781,
                "w": 38.32518768310547,
                "h": 27.860002517700195,
                "theta": 81.8698959350586
            },
            "height": 810,
            "width": 1080
        },
        {
            "geometryType": "obb",
            "obb": {
                "xc": 212.38137817382812,
                "yc": 775.4121704101562,
                "w": 56.63969421386719,
                "h": 46.35154724121094,
                "theta": 66.25050354003906
            },
            "height": 810,
            "width": 1080
        }
    ]
}