{
    "objects": [
        {
            "geometryType": "obb",
            "obb": {
                "xc": 348.21661376953125,
                "yc": 194.26258850097656,
                "w": 179.793701171875,
                "h": 45.11090087890625,
                "theta": 159.40396881103516
            },
            "height": 500,
            "width": 755
        },
        {
            "geometryType": "obb",
            "obb": {
                "xc": 485.47918701171875,
                "yc": 184.1730194091797,
                "w": 100.03836059570312,
                "h": 44.31053924560547,
                "theta": 19.855215072631836
            },
            "height": 500,
            "width": 755
        },
        {
            "geometryType": "obb",
            "obb": {
                "xc": 281.19207763671875,
                "yc": 396.3538818359375,
                "w": 190.04376220703125,
                "h": 61.398536682128906,
                "theta": 179.60486602783203
            },
            "height": 500,
            "width": 755
        },
        {
            "geometryType": "obb",
            "obb": {
                "xc": 509.99761962890625,
                "yc": 390.760009765625,
                "w": 221.48892211914062,
                "h": 63.65681076049805,
                "theta": 179.42705535888672
            },
            "height": 500,
            "width": 755
        },
        {
            "geometryType": "obb",
            "obb": {
                "xc": 383.2456970214844,
                "yc": 459.917724609375,
                "w": 155.00323486328125,
                "h": 78.83706665039062,
                "theta": 0.36964505910873413
            },
            "height": 500,
            "width": 755
        }
    ]
}