{
    "objects": [
        {
            "geometryType": "obb",
            "obb": {
                "xc": 484.881591796875,
                "yc": 245.9698028564453,
                "w": 645.0343627929688,
                "h": 137.67999267578125,
                "theta": 167.0680694580078
            },
            "height": 950,
            "width": 1500
        },
        {
            "geometryType": "obb",
            "obb": {
                "xc": 1054.701171875,
                "yc": 212.32247924804688,
                "w": 331.9788513183594,
                "h": 145.044189453125,
                "theta": 8.334362983703613
            },
            "height": 950,
            "width": 1500
        },
        {
            "geometryType": "obb",
            "obb": {
                "xc": 934.1629638671875,
                "yc": 663.0966796875,
                "w": 38.05259704589844,
                "h": 31.85065269470215,
                "theta": 176.98721313476562
            },
            "height": 950,
            "width": 1500
        },
        {
            "geometryType": "obb",
            "obb": {
                "xc": 300.0396728515625,
                "yc": 772.759521484375,
                "w": 354.43377685546875,
                "h": 77.10383605957031,
                "theta": 177.00469207763672
            },
            "height": 950,
            "width": 1500
        },
        {
            "geometryType": "obb",
            "obb": {
                "xc": 883.522216796875,
                "yc": 740.4757080078125,
                "w": 703.4487915039062,
                "h": 84.908203125,
                "theta": 177.33700561523438
            },
            "height": 950,
            "width": 1500
        }
    ]
}