{
    "objects": [
        {
            "geometryType": "obb",
            "obb": {
                "xc": 157.4053955078125,
                "yc": 172.02606201171875,
                "w": 173.47463989257812,
                "h": 74.0980453491211,
                "theta": 178.63607025146484
            },
            "height": 396,
            "width": 505
        },
        {
            "geometryType": "obb",
            "obb": {
                "xc": 173.46356201171875,
                "yc": 227.32627868652344,
                "w": 48.172916412353516,
                "h": 17.9737606048584,
                "theta": 176.90594482421875
            },
            "height": 396,
            "width": 505
        },
        {
            "geometryType": "obb",
            "obb": {
                "xc": 116.51752471923828,
                "yc": 256.7801818847656,
                "w": 30.12871551513672,
                "h": 15.469816207885742,
                "theta": 176.42366790771484
            },
            "height": 396,
            "width": 505
        },
        {
            "geometryType": "obb",
            "obb": {
                "xc": 155.68673706054688,
                "yc": 254.51788330078125,
                "w": 50.03266906738281,
                "h": 16.57296371459961,
                "theta": 176.72950744628906
            },
            "height": 396,
            "width": 505
        },
        {
            "geometryType": "obb",
            "obb": {
                "xc": 198.49639892578125,
                "yc": 252.6938018798828,
                "w": 33.993839263916016,
                "h": 17.351022720336914,
                "theta": 176.3086166381836
            },
            "height": 396,
            "width": 505
        },
        {
            "geometryType": "obb",
            "obb": {
                "xc": 141.076904296875,
                "yc": 282.3846130371094,
                "w": 29.177228927612305,
                "h": 18.416046142578125,
                "theta": 176.8201675415039
            },
            "height": 396,
            "width": 505
        },
        {
            "geometryType": "obb",
            "obb": {
                "xc": 182.05345153808594,
                "yc": 279.9085998535156,
                "w": 51.08816146850586,
                "h": 18.849769592285156,
                "theta": 176.633544921875
            },
            "height": 396,
            "width": 505
        },
        {
            "geometryType": "obb",
            "obb": {
                "xc": 140.89634704589844,
                "yc": 308.56707763671875,
                "w": 25.951412200927734,
                "h": 18.11077308654785,
                "theta": 173.6598129272461
            },
            "height": 396,
            "width": 505
        },
        {
            "geometryType": "obb",
            "obb": {
                "xc": 167.3640594482422,
                "yc": 307.3224792480469,
                "w": 24.081512451171875,
                "h": 16.733806610107422,
                "theta": 174.5596694946289
            },
            "height": 396,
            "width": 505
        },
        {
            "geometryType": "obb",
            "obb": {
                "xc": 142.1219482421875,
                "yc": 337.5975646972656,
                "w": 28.1600399017334,
                "h": 20.87156105041504,
                "theta": 173.6598129272461
            },
            "height": 396,
            "width": 505
        },
        {
            "geometryType": "obb",
            "obb": {
                "xc": 190.42681884765625,
                "yc": 330.84149169921875,
                "w": 39.31362533569336,
                "h": 17.889907836914062,
                "theta": 173.6598129272461
            },
            "height": 396,
            "width": 505
        },
        {
            "geometryType": "obb",
            "obb": {
                "xc": 145.0,
                "yc": 208.5,
                "w": 26.0,
                "h": 11.0,
                "theta": -0.0
            },
            "height": 396,
            "width": 505
        },
        {
            "geometryType": "obb",
            "obb": {
                "xc": 173.5,
                "yc": 208.5,
                "w": 23.0,
                "h": 13.0,
                "theta": 180.0
            },
            "height": 396,
            "width": 505
        },
        {
            "geometryType": "obb",
            "obb": {
                "xc": 135.5,
                "yc": 229.5,
                "w": 27.0,
                "h": 15.0,
                "theta": 0.0
            },
            "height": 396,
            "width": 505
        },
        {
            "geometryType": "obb",
            "obb": {
                "xc": 116.02645874023438,
                "yc": 285.3441162109375,
                "w": 15.032514572143555,
                "h": 13.88206672668457,
                "theta": 175.60128784179688
            },
            "height": 396,
            "width": 505
        },
        {
            "geometryType": "obb",
            "obb": {
                "xc": 187.0,
                "yc": 305.0,
                "w": 18.0,
                "h": 16.0,
                "theta": 180.0
            },
            "height": 396,
            "width": 505
        },
        {
            "geometryType": "obb",
            "obb": {
                "xc": 117.35977172851562,
                "yc": 339.23779296875,
                "w": 21.644580841064453,
                "h": 16.012571334838867,
                "theta": 173.6598129272461
            },
            "height": 396,
            "width": 505
        },
        {
            "geometryType": "obb",
            "obb": {
                "xc": 164.5172576904297,
                "yc": 335.2069091796875,
                "w": 13.61945915222168,
                "h": 10.131549835205078,
                "theta": 85.2363510131836
            },
            "height": 396,
            "width": 505
        }
    ]
}