{
    "objects": [
        {
            "geometryType": "obb",
            "obb": {
                "xc": 736.85693359375,
                "yc": 171.48919677734375,
                "w": 780.9292602539062,
                "h": 297.0267333984375,
                "theta": 174.2201156616211
            },
            "height": 904,
            "width": 1280
        },
        {
            "geometryType": "obb",
            "obb": {
                "xc": 782.2786865234375,
                "yc": 500.4259033203125,
                "w": 371.55682373046875,
                "h": 71.0594253540039,
                "theta": 174.5596694946289
            },
            "height": 904,
            "width": 1280
        },
        {
            "geometryType": "obb",
            "obb": {
                "xc": 531.1220703125,
                "yc": 670.5671997070312,
                "w": 425.0539855957031,
                "h": 176.57351684570312,
                "theta": 38.932769775390625
            },
            "height": 904,
            "width": 1280
        },
        {
            "geometryType": "obb",
            "obb": {
                "xc": 970.9832153320312,
                "yc": 652.6072998046875,
                "w": 499.4329528808594,
                "h": 202.13821411132812,
                "theta": 139.3066177368164
            },
            "height": 904,
            "width": 1280
        },
        {
            "geometryType": "obb",
            "obb": {
                "xc": 1159.2213134765625,
                "yc": 836.2928466796875,
                "w": 207.40780639648438,
                "h": 104.61996459960938,
                "theta": 176.40643310546875
            },
            "height": 904,
            "width": 1280
        },
        {
            "geometryType": "obb",
            "obb": {
                "xc": 691.6685791015625,
                "yc": 339.79833984375,
                "w": 264.9100036621094,
                "h": 207.60203552246094,
                "theta": 174.8826904296875
            },
            "height": 904,
            "width": 1280
        }
    ]
}