{
    "objects": [
        {
            "geometryType": "obb",
            "obb": {
                "xc": 1137.0,
                "yc": 182.5,
                "w": 68.0,
                "h": 43.0,
                "theta": 180.0
            },
            "height": 1280,
            "width": 1280
        },
        {
            "geometryType": "obb",
            "obb": {
                "xc": 483.151123046875,
                "yc": 369.2073974609375,
                "w": 181.88726806640625,
                "h": 77.4733657836914,
                "theta": 151.3558120727539
            },
            "height": 1280,
            "width": 1280
        },
        {
            "geometryType": "obb",
            "obb": {
                "xc": 626.845458984375,
                "yc": 400.8359375,
                "w": 127.78470611572266,
                "h": 45.64299774169922,
                "theta": 56.72511291503906
            },
            "height": 1280,
            "width": 1280
        },
        {
            "geometryType": "obb",
            "obb": {
                "xc": 553.3583374023438,
                "yc": 534.3223876953125,
                "w": 245.2410888671875,
                "h": 101.05595397949219,
                "theta": 3.7376298904418945
            },
            "height": 1280,
            "width": 1280
        },
        {
            "geometryType": "obb",
            "obb": {
                "xc": 938.5,
                "yc": 757.5000610351562,
                "w": 90.50968170166016,
                "h": 33.941131591796875,
                "theta": 135.0
            },
            "height": 1280,
            "width": 1280
        },
        {
            "geometryType": "obb",
            "obb": {
                "xc": 996.2647094726562,
                "yc": 766.5588989257812,
                "w": 66.56004333496094,
                "h": 30.18887710571289,
                "theta": 51.51980209350586
            },
            "height": 1280,
            "width": 1280
        },
        {
            "geometryType": "obb",
            "obb": {
                "xc": 965.1585083007812,
                "yc": 834.6453247070312,
                "w": 104.33621215820312,
                "h": 48.64969253540039,
                "theta": 177.51044464111328
            },
            "height": 1280,
            "width": 1280
        },
        {
            "geometryType": "obb",
            "obb": {
                "xc": 533.7335205078125,
                "yc": 887.8131103515625,
                "w": 107.35202026367188,
                "h": 28.478469848632812,
                "theta": 173.5411834716797
            },
            "height": 1280,
            "width": 1280
        },
        {
            "geometryType": "obb",
            "obb": {
                "xc": 516.6343383789062,
                "yc": 929.6273193359375,
                "w": 58.46365737915039,
                "h": 37.185482025146484,
                "theta": 167.15229034423828
            },
            "height": 1280,
            "width": 1280
        },
        {
            "geometryType": "obb",
            "obb": {
                "xc": 544.99267578125,
                "yc": 1018.4219970703125,
                "w": 102.25948333740234,
                "h": 19.07891845703125,
                "theta": 170.9982452392578
            },
            "height": 1280,
            "width": 1280
        },
        {
            "geometryType": "obb",
            "obb": {
                "xc": 1030.524658203125,
                "yc": 908.8374633789062,
                "w": 46.391700744628906,
                "h": 23.048856735229492,
                "theta": 178.31531524658203
            },
            "height": 1280,
            "width": 1280
        },
        {
            "geometryType": "obb",
            "obb": {
                "xc": 45.49444580078125,
                "yc": 902.1385498046875,
                "w": 84.57460021972656,
                "h": 29.02733039855957,
                "theta": 179.11859893798828
            },
            "height": 1280,
            "width": 1280
        },
        {
            "geometryType": "obb",
            "obb": {
                "xc": 1218.0,
                "yc": 260.5,
                "w": 40.0,
                "h": 25.0,
                "theta": -0.0
            },
            "height": 1280,
            "width": 1280
        },
        {
            "geometryType": "obb",
            "obb": {
                "xc": 1031.7713623046875,
                "yc": 891.6299438476562,
                "w": 31.91206932067871,
                "h": 17.748071670532227,
                "theta": 1.9749339818954468
            },
            "height": 1280,
            "width": 1280
        },
        {
            "geometryType": "obb",
            "obb": {
                "xc": 19.16580581665039,
                "yc": 925.1398315429688,
                "w": 31.016122817993164,
                "h": 20.731151580810547,
                "theta": 178.1523895263672
            },
            "height": 1280,
            "width": 1280
        },
        {
            "geometryType": "obb",
            "obb": {
                "xc": 55.5,
                "yc": 923.0,
                "w": 33.0,
                "h": 18.0,
                "theta": -0.0
            },
            "height": 1280,
            "width": 1280
        }
    ]
}