{
    "objects": [
        {
            "geometryType": "obb",
            "obb": {
                "xc": 167.82064819335938,
                "yc": 214.66943359375,
                "w": 153.03817749023438,
                "h": 61.14289474487305,
                "theta": 161.40892791748047
            },
            "height": 500,
            "width": 375
        },
        {
            "geometryType": "obb",
            "obb": {
                "xc": 192.55882263183594,
                "yc": 303.73529052734375,
                "w": 119.570068359375,
                "h": 53.600379943847656,
                "theta": 165.96376037597656
            },
            "height": 500,
            "width": 375
        },
        {
            "geometryType": "obb",
            "obb": {
                "xc": 14.5,
                "yc": 76.5,
                "w": 23.0,
                "h": 21.0,
                "theta": -0.0
            },
            "height": 500,
            "width": 375
        },
        {
            "geometryType": "obb",
            "obb": {
                "xc": 121.30491638183594,
                "yc": 297.64306640625,
                "w": 27.632810592651367,
                "h": 22.95566177368164,
                "theta": 53.74616622924805
            },
            "height": 500,
            "width": 375
        },
        {
            "geometryType": "obb",
            "obb": {
                "xc": 224.0,
                "yc": 482.0,
                "w": 46.0,
                "h": 16.0,
                "theta": -0.0
            },
            "height": 500,
            "width": 375
        },
        {
            "geometryType": "obb",
            "obb": {
                "xc": 266.0,
                "yc": 484.0,
                "w": 28.0,
                "h": 22.0,
                "theta": -0.0
            },
            "height": 500,
            "width": 375
        },
        {
            "geometryType": "obb",
            "obb": {
                "xc": 306.1568298339844,
                "yc": 483.7357177734375,
                "w": 47.00088119506836,
                "h": 17.44319725036621,
                "theta": 2.385944128036499
            },
            "height": 500,
            "width": 375
        },
        {
            "geometryType": "obb",
            "obb": {
                "xc": 346.37896728515625,
                "yc": 482.64166259765625,
                "w": 31.966325759887695,
                "h": 16.113107681274414,
                "theta": 4.969740867614746
            },
            "height": 500,
            "width": 375
        }
    ]
}