{
    "objects": [
        {
            "geometryType": "obb",
            "obb": {
                "xc": 74.88353729248047,
                "yc": 254.6259002685547,
                "w": 82.46211242675781,
                "h": 37.69003677368164,
                "theta": 140.90614318847656
            },
            "height": 624,
            "width": 1024
        },
        {
            "geometryType": "obb",
            "obb": {
                "xc": 235.49038696289062,
                "yc": 202.49002075195312,
                "w": 231.11244201660156,
                "h": 52.91140365600586,
                "theta": 1.1233028173446655
            },
            "height": 624,
            "width": 1024
        },
        {
            "geometryType": "obb",
            "obb": {
                "xc": 164.3262939453125,
                "yc": 470.5448303222656,
                "w": 121.31145477294922,
                "h": 40.3112678527832,
                "theta": 7.062602519989014
            },
            "height": 624,
            "width": 1024
        },
        {
            "geometryType": "obb",
            "obb": {
                "xc": 320.52703857421875,
                "yc": 486.6935729980469,
                "w": 144.4974365234375,
                "h": 34.04420471191406,
                "theta": 5.04245138168335
            },
            "height": 624,
            "width": 1024
        },
        {
            "geometryType": "obb",
            "obb": {
                "xc": 778.833984375,
                "yc": 118.32670593261719,
                "w": 47.08430099487305,
                "h": 25.54393768310547,
                "theta": 49.57392501831055
            },
            "height": 624,
            "width": 1024
        },
        {
            "geometryType": "obb",
            "obb": {
                "xc": 790.9555053710938,
                "yc": 82.54214477539062,
                "w": 75.50662994384766,
                "h": 38.161094665527344,
                "theta": 170.21759033203125
            },
            "height": 624,
            "width": 1024
        },
        {
            "geometryType": "obb",
            "obb": {
                "xc": 837.2861938476562,
                "yc": 120.53973388671875,
                "w": 65.53756713867188,
                "h": 31.97088623046875,
                "theta": 97.90716314315796
            },
            "height": 624,
            "width": 1024
        },
        {
            "geometryType": "obb",
            "obb": {
                "xc": 670.7876586914062,
                "yc": 524.5396728515625,
                "w": 80.47943878173828,
                "h": 30.36766815185547,
                "theta": 7.853313446044922
            },
            "height": 624,
            "width": 1024
        },
        {
            "geometryType": "obb",
            "obb": {
                "xc": 789.0670166015625,
                "yc": 554.5257568359375,
                "w": 73.4095230102539,
                "h": 29.851173400878906,
                "theta": 156.03751373291016
            },
            "height": 624,
            "width": 1024
        },
        {
            "geometryType": "obb",
            "obb": {
                "xc": 630.0669555664062,
                "yc": 230.5130157470703,
                "w": 65.54444122314453,
                "h": 22.59220314025879,
                "theta": 3.8785247802734375
            },
            "height": 624,
            "width": 1024
        },
        {
            "geometryType": "obb",
            "obb": {
                "xc": 706.5215454101562,
                "yc": 234.73159790039062,
                "w": 91.11933135986328,
                "h": 23.304000854492188,
                "theta": 4.600095748901367
            },
            "height": 624,
            "width": 1024
        },
        {
            "geometryType": "obb",
            "obb": {
                "xc": 569.5123901367188,
                "yc": 288.27215576171875,
                "w": 48.13212203979492,
                "h": 20.842117309570312,
                "theta": 177.39744567871094
            },
            "height": 624,
            "width": 1024
        },
        {
            "geometryType": "obb",
            "obb": {
                "xc": 634.5206298828125,
                "yc": 286.4891357421875,
                "w": 68.63094329833984,
                "h": 21.74527931213379,
                "theta": 178.80650329589844
            },
            "height": 624,
            "width": 1024
        },
        {
            "geometryType": "obb",
            "obb": {
                "xc": 706.9906005859375,
                "yc": 284.5409851074219,
                "w": 69.65896606445312,
                "h": 19.812198638916016,
                "theta": 178.8308563232422
            },
            "height": 624,
            "width": 1024
        },
        {
            "geometryType": "obb",
            "obb": {
                "xc": 773.0000610351562,
                "yc": 282.5000305175781,
                "w": 55.63239669799805,
                "h": 28.249528884887695,
                "theta": 174.7099151611328
            },
            "height": 624,
            "width": 1024
        },
        {
            "geometryType": "obb",
            "obb": {
                "xc": 773.218017578125,
                "yc": 394.05633544921875,
                "w": 108.53043365478516,
                "h": 25.584890365600586,
                "theta": 26.175289154052734
            },
            "height": 624,
            "width": 1024
        },
        {
            "geometryType": "obb",
            "obb": {
                "xc": 837.115478515625,
                "yc": 422.60540771484375,
                "w": 56.54661560058594,
                "h": 22.75005340576172,
                "theta": 19.179006576538086
            },
            "height": 624,
            "width": 1024
        },
        {
            "geometryType": "obb",
            "obb": {
                "xc": 949.3651123046875,
                "yc": 368.7796325683594,
                "w": 67.2929458618164,
                "h": 21.768505096435547,
                "theta": 25.76932716369629
            },
            "height": 624,
            "width": 1024
        },
        {
            "geometryType": "obb",
            "obb": {
                "xc": 383.3013000488281,
                "yc": 245.25982666015625,
                "w": 24.625093460083008,
                "h": 24.625093460083008,
                "theta": 37.405357360839844
            },
            "height": 624,
            "width": 1024
        },
        {
            "geometryType": "obb",
            "obb": {
                "xc": 454.7274169921875,
                "yc": 328.3133850097656,
                "w": 39.33638000488281,
                "h": 29.014741897583008,
                "theta": 64.65382385253906
            },
            "height": 624,
            "width": 1024
        },
        {
            "geometryType": "obb",
            "obb": {
                "xc": 608.5,
                "yc": 518.0,
                "w": 33.0,
                "h": 30.0,
                "theta": 180.0
            },
            "height": 624,
            "width": 1024
        },
        {
            "geometryType": "obb",
            "obb": {
                "xc": 268.3572692871094,
                "yc": 385.33270263671875,
                "w": 77.30094909667969,
                "h": 38.32662582397461,
                "theta": 99.72757911682129
            },
            "height": 624,
            "width": 1024
        },
        {
            "geometryType": "obb",
            "obb": {
                "xc": 697.4801025390625,
                "yc": 406.8304443359375,
                "w": 143.23251342773438,
                "h": 29.02630043029785,
                "theta": 179.474365234375
            },
            "height": 624,
            "width": 1024
        },
        {
            "geometryType": "obb",
            "obb": {
                "xc": 664.5816650390625,
                "yc": 431.61920166015625,
                "w": 74.9788818359375,
                "h": 16.220657348632812,
                "theta": 0.795723557472229
            },
            "height": 624,
            "width": 1024
        },
        {
            "geometryType": "obb",
            "obb": {
                "xc": 46.999996185302734,
                "yc": 603.4999389648438,
                "w": 61.99999237060547,
                "h": 10.999998092651367,
                "theta": 0.0
            },
            "height": 624,
            "width": 1024
        }
    ]
}